genai_rest_builder/__init__.py
genai_rest_builder/cli.py
genai_rest_builder/constants.py
genai_rest_builder/genai_langserve_codegen.py
genai_rest_builder/_yaml/__init__.py
genai_rest_builder/yaml/__init__.py
genai_rest_builder/yaml/composer.py
genai_rest_builder/yaml/constructor.py
genai_rest_builder/yaml/cyaml.py
genai_rest_builder/yaml/dumper.py
genai_rest_builder/yaml/emitter.py
genai_rest_builder/yaml/error.py
genai_rest_builder/yaml/events.py
genai_rest_builder/yaml/loader.py
genai_rest_builder/yaml/nodes.py
genai_rest_builder/yaml/parser.py
genai_rest_builder/yaml/reader.py
genai_rest_builder/yaml/representer.py
genai_rest_builder/yaml/resolver.py
genai_rest_builder/yaml/scanner.py
genai_rest_builder/yaml/serializer.py
genai_rest_builder/yaml/tokens.py
genai_rest_builder-0.2.3.dist-info/LICENSE.txt
genai_rest_builder-0.2.3.dist-info/METADATA
genai_rest_builder-0.2.3.dist-info/WHEEL
genai_rest_builder-0.2.3.dist-info/entry_points.txt
genai_rest_builder-0.2.3.dist-info/top_level.txt
genai_rest_builder-0.2.3.dist-info/RECORD
