Metadata-Version: 2.1
Name: genai_rest_builder
Version: 0.2.3
Summary: A tool to generate python code with GenAI RestAPIs.
Author-email: Biprajeet Kar <biprokvs@gmail.com>
Maintainer-email: Biprajeet Kar <biprokvs@gmail.com>
License: MIT License
Classifier: Programming Language :: Python :: 3
Classifier: License :: OSI Approved :: MIT License
Classifier: Operating System :: OS Independent
Requires-Python: >=3.9
License-File: LICENSE.txt
Requires-Dist: click
